vscode_config_generator/__init__.py
vscode_config_generator/cli.py
vscode_config_generator/generator.py
vscode_config_generator-2.1.0.dist-info/METADATA
vscode_config_generator-2.1.0.dist-info/WHEEL
vscode_config_generator-2.1.0.dist-info/entry_points.txt
vscode_config_generator-2.1.0.dist-info/top_level.txt
vscode_config_generator-2.1.0.dist-info/RECORD
