Metadata-Version: 2.1
Name: vscode-config-generator
Version: 2.1.0
Summary: Generate VS Code configurations for projects
Classifier: Programming Language :: Python :: 3
Classifier: License :: OSI Approved :: MIT License
Classifier: Operating System :: OS Independent
Requires-Python: >=3.6
